jcl/__init__.py
jcl/cli/__init__.py
pyjcl-0.1.0.dist-info/entry_points.txt
pyjcl-0.1.0.dist-info/WHEEL
pyjcl-0.1.0.dist-info/METADATA
pyjcl-0.1.0.dist-info/RECORD
