Metadata-Version: 2.1
Name: pyjcl
Version: 0.1.0
Summary: Jammy commandline
License: MIT
Author: Qinsheng
Author-email: qsh.zh27@gmail.com
Requires-Python: >=3.7,<4.0
Classifier: License :: OSI Approved :: MIT License
Classifier: Programming Language :: Python :: 3
Classifier: Programming Language :: Python :: 3.7
Classifier: Programming Language :: Python :: 3.8
Classifier: Programming Language :: Python :: 3.9
